mini_lambda/__init__.py
mini_lambda/_version.py
mini_lambda/base.py
mini_lambda/generated_magic.py
mini_lambda/generated_magic_replacements.py
mini_lambda/main.py
mini_lambda/py.typed
mini_lambda/symbols/__init__.py
mini_lambda/symbols/builtins.py
mini_lambda/symbols/decimal_.py
mini_lambda/symbols/math_.py
mini_lambda/vars/__init__.py
mini_lambda/vars/base.py
mini_lambda/vars/numpy_.py
mini_lambda/vars/pandas_.py
mini_lambda-2.2.3.dist-info/LICENSE
mini_lambda-2.2.3.dist-info/METADATA
mini_lambda-2.2.3.dist-info/WHEEL
mini_lambda-2.2.3.dist-info/top_level.txt
mini_lambda-2.2.3.dist-info/RECORD
