Metadata-Version: 2.1
Name: mini-lambda
Version: 2.2.3
Summary: Simple lambda functions without `lambda x:` and with string conversion capability.
Home-page: https://github.com/smarie/python-mini-lambda
Maintainer: Sylvain MARIE
Maintainer-email: sylvain.marie@schneider-electric.com
License: BSD 3-Clause
Download-URL: https://github.com/smarie/python-mini-lambda/tarball/2.2.3
Keywords: mini minimal lambda expr expression simple print string func function symbol symbolic
Platform: UNKNOWN
Classifier: Development Status :: 5 - Production/Stable
Classifier: Intended Audience :: Developers
Classifier: Topic :: Software Development :: Libraries :: Python Modules
Classifier: License :: OSI Approved :: BSD License
Classifier: Programming Language :: Python :: 2.7
Classifier: Programming Language :: Python :: 3.5
Classifier: Programming Language :: Python :: 3.6
Classifier: Programming Language :: Python :: 3.7
